jpreprocess_mod-0.1.7.dist-info/METADATA
jpreprocess_mod-0.1.7.dist-info/WHEEL
jpreprocess_mod/__init__.py
jpreprocess_mod/dictionary.py
jpreprocess_mod/jpreprocess_mod.cpython-38-powerpc64le-linux-gnu.so
jpreprocess_mod/jpreprocess_mod.pyi
jpreprocess_mod/py.typed
jpreprocess_mod-0.1.7.dist-info/RECORD
