Metadata-Version: 2.4
Name: jpreprocess_mod
Version: 0.1.7
Classifier: Programming Language :: Rust
Classifier: Programming Language :: Python :: Implementation :: CPython
Classifier: Programming Language :: Python :: Implementation :: PyPy
Classifier: License :: OSI Approved :: BSD License
Classifier: Topic :: Scientific/Engineering
Classifier: Topic :: Software Development
Classifier: Intended Audience :: Science/Research
Classifier: Intended Audience :: Developers
Requires-Dist: importlib-resources ; python_full_version < '3.9'
Requires-Dist: tqdm ; extra == 'progress'
Requires-Dist: pytest>=8.0.1 ; extra == 'dev'
Provides-Extra: progress
Provides-Extra: dev
Requires-Python: >=3.8, <=3.12
